nohands/__init__.py
nohands/__main__.py
nohands/demo.py
nohands-0.2.0.dist-info/METADATA
nohands-0.2.0.dist-info/WHEEL
nohands-0.2.0.dist-info/entry_points.txt
nohands-0.2.0.dist-info/top_level.txt
nohands-0.2.0.dist-info/RECORD
