Metadata-Version: 2.1
Name: nohands
Version: 0.2.0
Summary: A little library for effortless demos
Home-page: https://github.com/nirs/nohands
Author: Nir Soffer
Author-email: nirsof@gmail.com
License: MIT
Project-URL: Source, https://github.com/nirs/nohands
Project-URL: Bug Tracker, https://github.com/nirs/nohands/issues
Classifier: Operating System :: OS Independent
Classifier: Development Status :: 4 - Beta
Classifier: Environment :: Console
Classifier: Intended Audience :: Developers
Classifier: Topic :: Utilities
Requires-Dist: PyYAML
